hdl/fir_filter.sv
`timescale 1ns / 1ps
`default_nettype none
module fir_filter #(
    parameter WIDTH = 8
) (
    input wire rst_in,
    input wire signed [WIDTH-1:0] audio_in,
    input wire valid_in,
    input wire clk_in,
    output logic signed [WIDTH:0] filtered_audio,
    output logic data_ready
);

    logic [6:0] counter;
    logic signed [(WIDTH+8)-1:0] accumulator;
    //logic signed [50:0] accumulator;
    logic signed [WIDTH+8-1:0] COEFFICIENTS [31:0];
    logic signed [WIDTH-1:0] delay_line [31:0];
    logic signed [WIDTH-1:0] delay_line_counter;
    logic signed [(WIDTH+8)-1:0] dbg2;
    logic signed [WIDTH+8-1:0] coeff;
    logic signed [WIDTH-1:0] cur;
    logic multiply;
    initial begin
        COEFFICIENTS[0] = -1;
        COEFFICIENTS[1] = -2;
        COEFFICIENTS[2] = -2;
        COEFFICIENTS[3] = 0;
        COEFFICIENTS[4] = 5;
        COEFFICIENTS[5] = 10;
        COEFFICIENTS[6] = 10;
        COEFFICIENTS[7] = 0;
        COEFFICIENTS[8] = -19;
        COEFFICIENTS[9] = -37;
        COEFFICIENTS[10] = -36;
        COEFFICIENTS[11] = 0;
        COEFFICIENTS[12] = 70;
        COEFFICIENTS[13] = 157;
        COEFFICIENTS[14] = 229;
        COEFFICIENTS[15] = 257;
        COEFFICIENTS[16] = 229;
        COEFFICIENTS[17] = 157;
        COEFFICIENTS[18] = 70;
        COEFFICIENTS[19] = 0;
        COEFFICIENTS[20] = -36;
        COEFFICIENTS[21] = -37;
        COEFFICIENTS[22] = -19;
        COEFFICIENTS[23] = 0;
        COEFFICIENTS[24] = 10;
        COEFFICIENTS[25] = 10;
        COEFFICIENTS[26] = 5;
        COEFFICIENTS[27] = 0;
        COEFFICIENTS[28] = -2;
        COEFFICIENTS[29] = -2;
        COEFFICIENTS[30] = -1;
        COEFFICIENTS[31] = 0;
    end
    always_ff @(posedge clk_in) begin
        if(rst_in)begin
            data_ready <= 0;
            counter <= 0;
            filtered_audio <= 0; // Assign filtered_audio after counter reaches 32
            accumulator <= 0; // Reset accumulator after counter reaches 32 
            delay_line_counter <= 0;
            dbg2 <= 0;
            coeff <= 0;
            multiply <= 0;
        end 
        else begin
            if(valid_in) begin
                delay_line[0] <= audio_in[7:0];
                cur <= audio_in;
                multiply <= 1;
                counter <= 0;
                accumulator <= 0;
                data_ready <= 0;
            end
            else if(multiply)begin
                if(counter >= 32)begin
                    data_ready <= 1;
                    filtered_audio <= accumulator;
                    multiply <= 0;
                    accumulator <= 0;
                end
                else begin
                    data_ready <= 0;
                    //delay_line_counter <= delay_line[30]; //debug line
                    //dbg2 <= accumulator + (COEFFICIENTS[counter]*delay_line[counter]);//debug line
                    //coeff <= COEFFICIENTS[counter]; //debug line
                    delay_line[counter] <= (counter ==0) ? cur:delay_line[counter-1]; //circular shift
                    accumulator <= accumulator + (COEFFICIENTS[counter]*delay_line[counter]);
                    counter <= counter + 1;
                end
            end
            else begin
                data_ready <= 0;
            end
        end
    end


endmodule
`default_nettype wire

hdl/sine.sv
`timescale 1ns / 1ps
`default_nettype none // prevents system from inferring an undeclared logic (good practice)

//Sine Wave Generator
module sine_generator_750 (
  input wire clk_in,
  input wire rst_in, //clock and reset
  input wire step_in, //trigger a phase step (rate at which you run sine generator)
  output logic signed [7:0] amp_out); //output phase in 2's complement

  parameter PHASE_INCR = 32'b0000_1011_0100_1011_0100_1011_0100_1011; //17khz
  //parameter PHASE_INCR = 32'b1000_0000_0000_0000_0000_0000_0000_0000>>3; //1/16th of 12 khz is 750 Hz
  logic [31:0] phase;
  logic [7:0] amp;
  logic [7:0] amp_pre;
  assign amp_pre = ({~amp[7],amp[6:0]}); //2's comp output (if not scaling)
  assign amp_out = amp_pre; //decrease volume so it isn't too loud!
  sine_lut lut_1(.clk_in(clk_in), .phase_in(phase[31:26]), .amp_out(amp));

  always_ff @(posedge clk_in)begin
    if (rst_in)begin
      phase <= 32'b0;
    end else if (step_in)begin
      phase <= phase+PHASE_INCR;
    end
  end
endmodule

module sine_generator_440 (
  input wire clk_in,
  input wire rst_in, //clock and reset
  input wire step_in, //trigger a phase step (rate at which you run sine generator)
  output logic signed [7:0] amp_out); //output phase in 2's complement
  parameter PHASE_INCR = 32'b0000_0110_1010_0000_0011_1001_1101_0011; //(2^32) / (17,000 / 440)
  //parameter PHASE_INCR = 32'b0000_1001_0110_0011_0011_1010_0001_1011; //(2^32) / (12,000 / 440)
  logic [31:0] phase;
  logic [7:0] amp;
  logic [7:0] amp_pre;
  assign amp_pre = ({~amp[7],amp[6:0]}); //2's comp output (if not scaling)
  assign amp_out = amp_pre; //decrease volume so it isn't too loud!
  sine_lut lut_1(.clk_in(clk_in), .phase_in(phase[31:26]), .amp_out(amp));

  always_ff @(posedge clk_in)begin
    if (rst_in)begin
      phase <= 32'b0;
    end else if (step_in)begin
      phase <= phase+PHASE_INCR;
    end
  end
endmodule

//6bit sine lookup, 8bit depth
module sine_lut(input wire [5:0] phase_in, input wire clk_in, output logic[7:0] amp_out);
  always_ff @(posedge clk_in)begin
    case(phase_in)
      6'd0: amp_out<=8'd128;
      6'd1: amp_out<=8'd140;
      6'd2: amp_out<=8'd152;
      6'd3: amp_out<=8'd165;
      6'd4: amp_out<=8'd176;
      6'd5: amp_out<=8'd188;
      6'd6: amp_out<=8'd198;
      6'd7: amp_out<=8'd208;
      6'd8: amp_out<=8'd218;
      6'd9: amp_out<=8'd226;
      6'd10: amp_out<=8'd234;
      6'd11: amp_out<=8'd240;
      6'd12: amp_out<=8'd245;
      6'd13: amp_out<=8'd250;
      6'd14: amp_out<=8'd253;
      6'd15: amp_out<=8'd254;
      6'd16: amp_out<=8'd255;
      6'd17: amp_out<=8'd254;
      6'd18: amp_out<=8'd253;
      6'd19: amp_out<=8'd250;
      6'd20: amp_out<=8'd245;
      6'd21: amp_out<=8'd240;
      6'd22: amp_out<=8'd234;
      6'd23: amp_out<=8'd226;
      6'd24: amp_out<=8'd218;
      6'd25: amp_out<=8'd208;
      6'd26: amp_out<=8'd198;
      6'd27: amp_out<=8'd188;
      6'd28: amp_out<=8'd176;
      6'd29: amp_out<=8'd165;
      6'd30: amp_out<=8'd152;
      6'd31: amp_out<=8'd140;
      6'd32: amp_out<=8'd128;
      6'd33: amp_out<=8'd115;
      6'd34: amp_out<=8'd103;
      6'd35: amp_out<=8'd90;
      6'd36: amp_out<=8'd79;
      6'd37: amp_out<=8'd67;
      6'd38: amp_out<=8'd57;
      6'd39: amp_out<=8'd47;
      6'd40: amp_out<=8'd37;
      6'd41: amp_out<=8'd29;
      6'd42: amp_out<=8'd21;
      6'd43: amp_out<=8'd15;
      6'd44: amp_out<=8'd10;
      6'd45: amp_out<=8'd5;
      6'd46: amp_out<=8'd2;
      6'd47: amp_out<=8'd1;
      6'd48: amp_out<=8'd0;
      6'd49: amp_out<=8'd1;
      6'd50: amp_out<=8'd2;
      6'd51: amp_out<=8'd5;
      6'd52: amp_out<=8'd10;
      6'd53: amp_out<=8'd15;
      6'd54: amp_out<=8'd21;
      6'd55: amp_out<=8'd29;
      6'd56: amp_out<=8'd37;
      6'd57: amp_out<=8'd47;
      6'd58: amp_out<=8'd57;
      6'd59: amp_out<=8'd67;
      6'd60: amp_out<=8'd79;
      6'd61: amp_out<=8'd90;
      6'd62: amp_out<=8'd103;
      6'd63: amp_out<=8'd115;
    endcase
  end
endmodule

`default_nettype wire

sim/lpf_tb.sv
`timescale 1ns / 1ps
`default_nettype none

module lpf_tb();

  logic clk_in;
  logic sys_rst;
  logic audio_sample_valid;
  logic signed [7:0] tone_440;
  logic fir_ready_for_input;
  logic fir_output_ready;
  logic [7:0] fir_out;
  localparam PDM_COUNT_PERIOD = 16; //do not change
  localparam NUM_PDM_SAMPLES = 128; //number of pdm in downsample/decimation/average
  sine_generator_440 sine_440(.clk_in(clk_in),
                .rst_in(sys_rst),
                .step_in(audio_sample_valid),
                .amp_out(tone_440));

  fir_filter fir(.audio_in(tone_440),
                .rst_in(sys_rst),
                .valid_in(audio_sample_valid),
                .clk_in(clk_in),
                .filtered_audio(fir_out),
                .data_ready(fir_output_ready));

  always begin
      #5;  //every 5 ns switch...so period of clock is 10 ns...100 MHz clock
      clk_in = !clk_in;
  end
  logic old_mic_clk; //prior mic clock for edge detection
  logic sampled_mic_data; //one bit grabbed/held values of mic
  logic pdm_signal_valid; //single-cycle signal at 4.352 MHz indicating pdm steps
  logic mic_clk;
  logic [8:0] m_clock_counter;
  logic [8:0] pdm_counter;
  assign pdm_signal_valid = mic_clk && ~old_mic_clk;


  //generate clock signal for microphone
  //microphone signal at ~4.352 MHz
  always_ff @(posedge clk_in)begin
    mic_clk <= m_clock_counter < PDM_COUNT_PERIOD/2;
    m_clock_counter <= (m_clock_counter==PDM_COUNT_PERIOD-1)?0:m_clock_counter+1;
    old_mic_clk <= mic_clk;
  end
  always_ff @(posedge clk_in)begin
    if (pdm_signal_valid)begin
      pdm_counter         <= (pdm_counter==NUM_PDM_SAMPLES)?0:pdm_counter + 1;
      audio_sample_valid  <= (pdm_counter==NUM_PDM_SAMPLES);
    end else begin
      audio_sample_valid <= 0;
    end
  end
  //initial block...this is our test simulation
  initial begin
    $dumpfile("lpf_tb.vcd"); //file to store value change dump (vcd)
    $dumpvars(0,lpf_tb);
    $display("Starting Sim"); //print nice message at start
    clk_in = 0;
    sys_rst = 0;
    old_mic_clk = 0;
    sampled_mic_data = 0;
    mic_clk = 0;
    m_clock_counter = 0;
    pdm_counter = 0;

    //out_sample = 0;
    #10;
    sys_rst = 1;
    #10;
    sys_rst = 0;
    #1000000;
    $display("Simulation finished");
    $finish;
  end
endmodule
`default_nettype wire

lpf_tb.vcd
$date
	Thu Nov 16 23:05:08 2023
$end
$version
	Icarus Verilog
$end
$timescale
	1ps
$end
$scope module lpf_tb $end
$var wire 1 ! pdm_signal_valid $end
$var wire 8 " tone_440 [7:0] $end
$var wire 1 # fir_output_ready $end
$var wire 8 $ fir_out [7:0] $end
$var parameter 32 % NUM_PDM_SAMPLES $end
$var parameter 32 & PDM_COUNT_PERIOD $end
$var reg 1 ' audio_sample_valid $end
$var reg 1 ( clk_in $end
$var reg 9 ) m_clock_counter [8:0] $end
$var reg 1 * mic_clk $end
$var reg 1 + old_mic_clk $end
$var reg 9 , pdm_counter [8:0] $end
$var reg 1 - sampled_mic_data $end
$var reg 1 . sys_rst $end
$scope module fir $end
$var wire 1 ( clk_in $end
$var wire 1 . rst_in $end
$var wire 1 ' valid_in $end
$var wire 8 / audio_in [7:0] $end
$var parameter 32 0 WIDTH $end
$var reg 16 1 accumulator [15:0] $end
$var reg 16 2 coeff [15:0] $end
$var reg 7 3 counter [6:0] $end
$var reg 8 4 cur [7:0] $end
$var reg 1 # data_ready $end
$var reg 16 5 dbg2 [15:0] $end
$var reg 8 6 delay_line_counter [7:0] $end
$var reg 9 7 filtered_audio [8:0] $end
$var reg 1 8 multiply $end
$upscope $end
$scope module sine_440 $end
$var wire 8 9 amp_out [7:0] $end
$var wire 1 ( clk_in $end
$var wire 1 . rst_in $end
$var wire 1 ' step_in $end
$var wire 8 : amp_pre [7:0] $end
$var wire 8 ; amp [7:0] $end
$var parameter 32 < PHASE_INCR $end
$var reg 32 = phase [31:0] $end
$scope module lut_1 $end
$var wire 1 ( clk_in $end
$var wire 6 > phase_in [5:0] $end
$var reg 8 ? amp_out [7:0] $end
$upscope $end
$upscope $end
$upscope $end
$enddefinitions $end
$comment Show the parameter values. $end
$dumpall
b1001011000110011101000011011 <
b1000 0
b10000 &
b10000000 %
$end
#0
$dumpvars
bx ?
bx >
bx =
bx ;
bx :
bx 9
x8
bx 7
bx 6
bx 5
bx 4
bx 3
bx 2
bx 1
bx /
0.
0-
b0 ,
0+
0*
b0 )
0(
x'
bx $
x#
bx "
0!
$end
#5000
1!
0#
b1 )
1*
0'
1(
#10000
0(
1.
#15000
0!
b0 $
b0 >
b1 ,
1+
b10 )
08
b0 2
b0 5
b0 6
b0 1
b0 7
b0 3
b0 =
1(
#20000
0(
0.
#25000
b0 "
b0 /
b0 9
b0 :
b10000000 ;
b10000000 ?
b11 )
1(
#30000
0(
#35000
b100 )
1(
#40000
0(
#45000
b101 )
1(
#50000
0(
#55000
b110 )
1(
#60000
0(
#65000
b111 )
1(
#70000
0(
#75000
b1000 )
1(
#80000
0(
#85000
b1001 )
0*
1(
#90000
0(
#95000
0+
b1010 )
1(
#100000
0(
#105000
b1011 )
1(
#110000
0(
#115000
b1100 )
1(
#120000
0(
#125000
b1101 )
1(
#130000
0(
#135000
b1110 )
1(
#140000
0(
#145000
b1111 )
1(
#150000
0(
#155000
b0 )
1(
#160000
0(
#165000
1!
b1 )
1*
1(
#170000
0(
#175000
0!
b10 ,
1+
b10 )
1(
#180000
0(
#185000
b11 )
1(
#190000
0(
#195000
b100 )
1(
#200000
0(
#205000
b101 )
1(
#210000
0(
#215000
b110 )
1(
#220000
0(
#225000
b111 )
1(
#230000
0(
#235000
b1000 )
1(
#240000
0(
#245000
b1001 )
0*
1(
#250000
0(
#255000
0+
b1010 )
1(
#260000
0(
#265000
b1011 )
1(
#270000
0(
#275000
b1100 )
1(
#280000
0(
#285000
b1101 )
1(
#290000
0(
#295000
b1110 )
1(
#300000
0(
#305000
b1111 )
1(
#310000
0(
#315000
b0 )
1(
#320000
0(
#325000
1!
b1 )
1*
1(
#330000
0(
#335000
0!
b11 ,
1+
b10 )
1(
#340000
0(
#345000
b11 )
1(
#350000
0(
#355000
b100 )
1(
#360000
0(
#365000
b101 )
1(
#370000
0(
#375000
b110 )
1(
#380000
0(
#385000
b111 )
1(
#390000
0(
#395000
b1000 )
1(
#400000
0(
#405000
b1001 )
0*
1(
#410000
0(
#415000
0+
b1010 )
1(
#420000
0(
#425000
b1011 )
1(
#430000
0(
#435000
b1100 )
1(
#440000
0(
#445000
b1101 )
1(
#450000
0(
#455000
b1110 )
1(
#460000
0(
#465000
b1111 )
1(
#470000
0(
#475000
b0 )
1(
#480000
0(
#485000
1!
b1 )
1*
1(
#490000
0(
#495000
0!
b100 ,
1+
b10 )
1(
#500000
0(
#505000
b11 )
1(
#510000
0(
#515000
b100 )
1(
#520000
0(
#525000
b101 )
1(
#530000
0(
#535000
b110 )
1(
#540000
0(
#545000
b111 )
1(
#550000
0(
#555000
b1000 )
1(
#560000
0(
#565000
b1001 )
0*
1(
#570000
0(
#575000
0+
b1010 )
1(
#580000
0(
#585000
b1011 )
1(
#590000
0(
#595000
b1100 )
1(
#600000
0(
#605000
b1101 )
1(
#610000
0(
#615000
b1110 )
1(
#620000
0(
#625000
b1111 )
1(
#630000
0(
#635000
b0 )
1(
#640000
0(
#645000
1!
b1 )
1*
1(
#650000
0(
#655000
0!
b101 ,
1+
b10 )
1(
#660000
0(
#665000
b11 )
1(
#670000
0(
#675000
b100 )
1(
#680000
0(
#685000
b101 )
1(
#690000
0(
#695000
b110 )
1(
#700000
0(
#705000
b111 )
1(
#710000
0(
#715000
b1000 )
1(
#720000
0(
#725000
b1001 )
0*
1(
#730000
0(
#735000
0+
b1010 )
1(
#740000
0(
#745000
b1011 )
1(
#750000
0(
#755000
b1100 )
1(
#760000
0(
#765000
b1101 )
1(
#770000
0(
#775000
b1110 )
1(
#780000
0(
#785000
b1111 )
1(
#790000
0(
#795000
b0 )
1(
#800000
0(
#805000
1!
b1 )
1*
1(
#810000
0(
#815000
0!
b110 ,
1+
b10 )
1(
#820000
0(
#825000
b11 )
1(
#830000
0(
#835000
b100 )
1(
#840000
0(
#845000
b101 )
1(
#850000
0(
#855000
b110 )
1(
#860000
0(
#865000
b111 )
1(
#870000
0(
#875000
b1000 )
1(
#880000
0(
#885000
b1001 )
0*
1(
#890000
0(
#895000
0+
b1010 )
1(
#900000
0(
#905000
b1011 )
1(
#910000
0(
#915000
b1100 )
1(
#920000
0(
#925000
b1101 )
1(
#930000
0(
#935000
b1110 )
1(
#940000
0(
#945000
b1111 )
1(
#950000
0(
#955000
b0 )
1(
#960000
0(
#965000
1!
b1 )
1*
1(
#970000
0(
#975000
0!
b111 ,
1+
b10 )
1(
#980000
0(
#985000
b11 )
1(
#990000
0(
#995000
b100 )
1(
#1000000
0(
#1005000
b101 )
1(
#1010000
0(
#1015000
b110 )
1(
#1020000
0(
#1025000
b111 )
1(
#1030000
0(
#1035000
b1000 )
1(
#1040000
0(
#1045000
b1001 )
0*
1(
#1050000
0(
#1055000
0+
b1010 )
1(
#1060000
0(
#1065000
b1011 )
1(
#1070000
0(
#1075000
b1100 )
1(
#1080000
0(
#1085000
b1101 )
1(
#1090000
0(
#1095000
b1110 )
1(
#1100000
0(
#1105000
b1111 )
1(
#1110000
0(
#1115000
b0 )
1(
#1120000
0(
#1125000
1!
b1 )
1*
1(
#1130000
0(
#1135000
0!
b1000 ,
1+
b10 )
1(
#1140000
0(
#1145000
b11 )
1(
#1150000
0(
#1155000
b100 )
1(
#1160000
0(
#1165000
b101 )
1(
#1170000
0(
#1175000
b110 )
1(
#1180000
0(
#1185000
b111 )
1(
#1190000
0(
#1195000
b1000 )
1(
#1200000
0(
#1205000
b1001 )
0*
1(
#1210000
0(
#1215000
0+
b1010 )
1(
#1220000
0(
#1225000
b1011 )
1(
#1230000
0(
#1235000
b1100 )
1(
#1240000
0(
#1245000
b1101 )
1(
#1250000
0(
#1255000
b1110 )
1(
#1260000
0(
#1265000
b1111 )
1(
#1270000
0(
#1275000
b0 )
1(
#1280000
0(
#1285000
1!
b1 )
1*
1(
#1290000
0(
#1295000
0!
b1001 ,
1+
b10 )
1(
#1300000
0(
#1305000
b11 )
1(
#1310000
0(
#1315000
b100 )
1(
#1320000
0(
#1325000
b101 )
1(
#1330000
0(
#1335000
b110 )
1(
#1340000
0(
#1345000
b111 )
1(
#1350000
0(
#1355000
b1000 )
1(
#1360000
0(
#1365000
b1001 )
0*
1(
#1370000
0(
#1375000
0+
b1010 )
1(
#1380000
0(
#1385000
b1011 )
1(
#1390000
0(
#1395000
b1100 )
1(
#1400000
0(
#1405000
b1101 )
1(
#1410000
0(
#1415000
b1110 )
1(
#1420000
0(
#1425000
b1111 )
1(
#1430000
0(
#1435000
b0 )
1(
#1440000
0(
#1445000
1!
b1 )
1*
1(
#1450000
0(
#1455000
0!
b1010 ,
1+
b10 )
1(
#1460000
0(
#1465000
b11 )
1(
#1470000
0(
#1475000
b100 )
1(
#1480000
0(
#1485000
b101 )
1(
#1490000
0(
#1495000
b110 )
1(
#1500000
0(
#1505000
b111 )
1(
#1510000
0(
#1515000
b1000 )
1(
#1520000
0(
#1525000
b1001 )
0*
1(
#1530000
0(
#1535000
0+
b1010 )
1(
#1540000
0(
#1545000
b1011 )
1(
#1550000
0(
#1555000
b1100 )
1(
#1560000
0(
#1565000
b1101 )
1(
#1570000
0(
#1575000
b1110 )
1(
#1580000
0(
#1585000
b1111 )
1(
#1590000
0(
#1595000
b0 )
1(
#1600000
0(
#1605000
1!
b1 )
1*
1(
#1610000
0(
#1615000
0!
b1011 ,
1+
b10 )
1(
#1620000
0(
#1625000
b11 )
1(
#1630000
0(
#1635000
b100 )
1(
#1640000
0(
#1645000
b101 )
1(
#1650000
0(
#1655000
b110 )
1(
#1660000
0(
#1665000
b111 )
1(
#1670000
0(
#1675000
b1000 )
1(
#1680000
0(
#1685000
b1001 )
0*
1(
#1690000
0(
#1695000
0+
b1010 )
1(
#1700000
0(
#1705000
b1011 )
1(
#1710000
0(
#1715000
b1100 )
1(
#1720000
0(
#1725000
b1101 )
1(
#1730000
0(
#1735000
b1110 )
1(
#1740000
0(
#1745000
b1111 )
1(
#1750000
0(
#1755000
b0 )
1(
#1760000
0(
#1765000
1!
b1 )
1*
1(
#1770000
0(
#1775000
0!
b1100 ,
1+
b10 )
1(
#1780000
0(
#1785000
b11 )
1(
#1790000
0(
#1795000
b100 )
1(
#1800000
0(
#1805000
b101 )
1(
#1810000
0(
#1815000
b110 )
1(
#1820000
0(
#1825000
b111 )
1(
#1830000
0(
#1835000
b1000 )
1(
#1840000
0(
#1845000
b1001 )
0*
1(
#1850000
0(
#1855000
0+
b1010 )
1(
#1860000
0(
#1865000
b1011 )
1(
#1870000
0(
#1875000
b1100 )
1(
#1880000
0(
#1885000
b1101 )
1(
#1890000
0(
#1895000
b1110 )
1(
#1900000
0(
#1905000
b1111 )
1(
#1910000
0(
#1915000
b0 )
1(
#1920000
0(
#1925000
1!
b1 )
1*
1(
#1930000
0(
#1935000
0!
b1101 ,
1+
b10 )
1(
#1940000
0(
#1945000
b11 )
1(
#1950000
0(
#1955000
b100 )
1(
#1960000
0(
#1965000
b101 )
1(
#1970000
0(
#1975000
b110 )
1(
#1980000
0(
#1985000
b111 )
1(
#1990000
0(
#1995000
b1000 )
1(
#2000000
0(
#2005000
b1001 )
0*
1(
#2010000
0(
#2015000
0+
b1010 )
1(
#2020000
0(
#2025000
b1011 )
1(
#2030000
0(
#2035000
b1100 )
1(
#2040000
0(
#2045000
b1101 )
1(
#2050000
0(
#2055000
b1110 )
1(
#2060000
0(
#2065000
b1111 )
1(
#2070000
0(
#2075000
b0 )
1(
#2080000
0(
#2085000
1!
b1 )
1*
1(
#2090000
0(
#2095000
0!
b1110 ,
1+
b10 )
1(
#2100000
0(
#2105000
b11 )
1(
#2110000
0(
#2115000
b100 )
1(
#2120000
0(
#2125000
b101 )
1(
#2130000
0(
#2135000
b110 )
1(
#2140000
0(
#2145000
b111 )
1(
#2150000
0(
#2155000
b1000 )
1(
#2160000
0(
#2165000
b1001 )
0*
1(
#2170000
0(
#2175000
0+
b1010 )
1(
#2180000
0(
#2185000
b1011 )
1(
#2190000
0(
#2195000
b1100 )
1(
#2200000
0(
#2205000
b1101 )
1(
#2210000
0(
#2215000
b1110 )
1(
#2220000
0(
#2225000
b1111 )
1(
#2230000
0(
#2235000
b0 )
1(
#2240000
0(
#2245000
1!
b1 )
1*
1(
#2250000
0(
#2255000
0!
b1111 ,
1+
b10 )
1(
#2260000
0(
#2265000
b11 )
1(
#2270000
0(
#2275000
b100 )
1(
#2280000
0(
#2285000
b101 )
1(
#2290000
0(
#2295000
b110 )
1(
#2300000
0(
#2305000
b111 )
1(
#2310000
0(
#2315000
b1000 )
1(
#2320000
0(
#2325000
b1001 )
0*
1(
#2330000
0(
#2335000
0+
b1010 )
1(
#2340000
0(
#2345000
b1011 )
1(
#2350000
0(
#2355000
b1100 )
1(
#2360000
0(
#2365000
b1101 )
1(
#2370000
0(
#2375000
b1110 )
1(
#2380000
0(
#2385000
b1111 )
1(
#2390000
0(
#2395000
b0 )
1(
#2400000
0(
#2405000
1!
b1 )
1*
1(
#2410000
0(
#2415000
0!
b10000 ,
1+
b10 )
1(
#2420000
0(
#2425000
b11 )
1(
#2430000
0(
#2435000
b100 )
1(
#2440000
0(
#2445000
b101 )
1(
#2450000
0(
#2455000
b110 )
1(
#2460000
0(
#2465000
b111 )
1(
#2470000
0(
#2475000
b1000 )
1(
#2480000
0(
#2485000
b1001 )
0*
1(
#2490000
0(
#2495000
0+
b1010 )
1(
#2500000
0(
#2505000
b1011 )
1(
#2510000
0(
#2515000
b1100 )
1(
#2520000
0(
#2525000
b1101 )
1(
#2530000
0(
#2535000
b1110 )
1(
#2540000
0(
#2545000
b1111 )
1(
#2550000
0(
#2555000
b0 )
1(
#2560000
0(
#2565000
1!
b1 )
1*
1(
#2570000
0(
#2575000
0!
b10001 ,
1+
b10 )
1(
#2580000
0(
#2585000
b11 )
1(
#2590000
0(
#2595000
b100 )
1(
#2600000
0(
#2605000
b101 )
1(
#2610000
0(
#2615000
b110 )
1(
#2620000
0(
#2625000
b111 )
1(
#2630000
0(
#2635000
b1000 )
1(
#2640000
0(
#2645000
b1001 )
0*
1(
#2650000
0(
#2655000
0+
b1010 )
1(
#2660000
0(
#2665000
b1011 )
1(
#2670000
0(
#2675000
b1100 )
1(
#2680000
0(
#2685000
b1101 )
1(
#2690000
0(
#2695000
b1110 )
1(
#2700000
0(
#2705000
b1111 )
1(
#2710000
0(
#2715000
b0 )
1(
#2720000
0(
#2725000
1!
b1 )
1*
1(
#2730000
0(
#2735000
0!
b10010 ,
1+
b10 )
1(
#2740000
0(
#2745000
b11 )
1(
#2750000
0(
#2755000
b100 )
1(
#2760000
0(
#2765000
b101 )
1(
#2770000
0(
#2775000
b110 )
1(
#2780000
0(
#2785000
b111 )
1(
#2790000
0(
#2795000
b1000 )
1(
#2800000
0(
#2805000
b1001 )
0*
1(
#2810000
0(
#2815000
0+
b1010 )
1(
#2820000
0(
#2825000
b1011 )
1(
#2830000
0(
#2835000
b1100 )
1(
#2840000
0(
#2845000
b1101 )
1(
#2850000
0(
#2855000
b1110 )
1(
#2860000
0(
#2865000
b1111 )
1(
#2870000
0(
#2875000
b0 )
1(
#2880000
0(
#2885000
1!
b1 )
1*
1(
#2890000
0(
#2895000
0!
b10011 ,
1+
b10 )
1(
#2900000
0(
#2905000
b11 )
1(
#2910000
0(
#2915000
b100 )
1(
#2920000
0(
#2925000
b101 )
1(
#2930000
0(
#2935000
b110 )
1(
#2940000
0(
#2945000
b111 )
1(
#2950000
0(
#2955000
b1000 )
1(
#2960000
0(
#2965000
b1001 )
0*
1(
#2970000
0(
#2975000
0+
b1010 )
1(
#2980000
0(
#2985000
b1011 )
1(
#2990000
0(
#2995000
b1100 )
1(
#3000000
0(
#3005000
b1101 )
1(
#3010000
0(
#3015000
b1110 )
1(
#3020000
0(
#3025000
b1111 )
1(
#3030000
0(
#3035000
b0 )
1(
#3040000
0(
#3045000
1!
b1 )
1*
1(
#3050000
0(
#3055000
0!
b10100 ,
1+
b10 )
1(
#3060000
0(
#3065000
b11 )
1(
#3070000
0(
#3075000
b100 )
1(
#3080000
0(
#3085000
b101 )
1(
#3090000
0(
#3095000
b110 )
1(
#3100000
0(
#3105000
b111 )
1(
#3110000
0(
#3115000
b1000 )
1(
#3120000
0(
#3125000
b1001 )
0*
1(
#3130000
0(
#3135000
0+
b1010 )
1(
#3140000
0(
#3145000
b1011 )
1(
#3150000
0(
#3155000
b1100 )
1(
#3160000
0(
#3165000
b1101 )
1(
#3170000
0(
#3175000
b1110 )
1(
#3180000
0(
#3185000
b1111 )
1(
#3190000
0(
#3195000
b0 )
1(
#3200000
0(
#3205000
1!
b1 )
1*
1(
#3210000
0(
#3215000
0!
b10101 ,
1+
b10 )
1(
#3220000
0(
#3225000
b11 )
1(
#3230000
0(
#3235000
b100 )
1(
#3240000
0(
#3245000
b101 )
1(
#3250000
0(
#3255000
b110 )
1(
#3260000
0(
#3265000
b111 )
1(
#3270000
0(
#3275000
b1000 )
1(
#3280000
0(
#3285000
b1001 )
0*
1(
#3290000
0(
#3295000
0+
b1010 )
1(
#3300000
0(
#3305000
b1011 )
1(
#3310000
0(
#3315000
b1100 )
1(
#3320000
0(
#3325000
b1101 )
1(
#3330000
0(
#3335000
b1110 )
1(
#3340000
0(
#3345000
b1111 )
1(
#3350000
0(
#3355000
b0 )
1(
#3360000
0(
#3365000
1!
b1 )
1*
1(
#3370000
0(
#3375000
0!
b10110 ,
1+
b10 )
1(
#3380000
0(
#3385000
b11 )
1(
#3390000
0(
#3395000
b100 )
1(
#3400000
0(
#3405000
b101 )
1(
#3410000
0(
#3415000
b110 )
1(
#3420000
0(
#3425000
b111 )
1(
#3430000
0(
#3435000
b1000 )
1(
#3440000
0(
#3445000
b1001 )
0*
1(
#3450000
0(
#3455000
0+
b1010 )
1(
#3460000
0(
#3465000
b1011 )
1(
#3470000
0(
#3475000
b1100 )
1(
#3480000
0(
#3485000
b1101 )
1(
#3490000
0(
#3495000
b1110 )
1(
#3500000
0(
#3505000
b1111 )
1(
#3510000
0(
#3515000
b0 )
1(
#3520000
0(
#3525000
1!
b1 )
1*
1(
#3530000
0(
#3535000
0!
b10111 ,
1+
b10 )
1(
#3540000
0(
#3545000
b11 )
1(
#3550000
0(
#3555000
b100 )
1(
#3560000
0(
#3565000
b101 )
1(
#3570000
0(
#3575000
b110 )
1(
#3580000
0(
#3585000
b111 )
1(
#3590000
0(
#3595000
b1000 )
1(
#3600000
0(
#3605000
b1001 )
0*
1(
#3610000
0(
#3615000
0+
b1010 )
1(
#3620000
0(
#3625000
b1011 )
1(
#3630000
0(
#3635000
b1100 )
1(
#3640000
0(
#3645000
b1101 )
1(
#3650000
0(
#3655000
b1110 )
1(
#3660000
0(
#3665000
b1111 )
1(
#3670000
0(
#3675000
b0 )
1(
#3680000
0(
#3685000
1!
b1 )
1*
1(
#3690000
0(
#3695000
0!
b11000 ,
1+
b10 )
1(
#3700000
0(
#3705000
b11 )
1(
#3710000
0(
#3715000
b100 )
1(
#3720000
0(
#3725000
b101 )
1(
#3730000
0(
#3735000
b110 )
1(
#3740000
0(
#3745000
b111 )
1(
#3750000
0(
#3755000
b1000 )
1(
#3760000
0(
#3765000
b1001 )
0*
1(
#3770000
0(
#3775000
0+
b1010 )
1(
#3780000
0(
#3785000
b1011 )
1(
#3790000
0(
#3795000
b1100 )
1(
#3800000
0(
#3805000
b1101 )
1(
#3810000
0(
#3815000
b1110 )
1(
#3820000
0(
#3825000
b1111 )
1(
#3830000
0(
#3835000
b0 )
1(
#3840000
0(
#3845000
1!
b1 )
1*
1(
#3850000
0(
#3855000
0!
b11001 ,
1+
b10 )
1(
#3860000
0(
#3865000
b11 )
1(
#3870000
0(
#3875000
b100 )
1(
#3880000
0(
#3885000
b101 )
1(
#3890000
0(
#3895000
b110 )
1(
#3900000
0(
#3905000
b111 )
1(
#3910000
0(
#3915000
b1000 )
1(
#3920000
0(
#3925000
b1001 )
0*
1(
#3930000
0(
#3935000
0+
b1010 )
1(
#3940000
0(
#3945000
b1011 )
1(
#3950000
0(
#3955000
b1100 )
1(
#3960000
0(
#3965000
b1101 )
1(
